LICENSE.txt
README.md
setup.py
dtspec/__init__.py
dtspec/api.py
dtspec/cli.py
dtspec/core.py
dtspec/db.py
dtspec/decorators.py
dtspec/expectations.py
dtspec/log.py
dtspec/shell.py
dtspec/specs.py
dtspec/version.py
dtspec.egg-info/PKG-INFO
dtspec.egg-info/SOURCES.txt
dtspec.egg-info/dependency_links.txt
dtspec.egg-info/entry_points.txt
dtspec.egg-info/requires.txt
dtspec.egg-info/top_level.txt